discordion/__init__.py
discordion/gpt.py
discordion/id.py
discordion/server.py
discordion/util.py
discordion/db/__init__.py
discordion/db/crud.py
discordion/tasks/__init__.py
discordion/tasks/tasks.py
examples/__init__.py
examples/Pokemon/__init__.py
examples/Pokemon/google.py
examples/Pokemon/main.py
examples/Pokemon/models.py
examples/Pokemon/tasks/__init__.py
examples/Pokemon/tasks/commute.py
examples/Pokemon/tasks/pokemon.py
discordion-0.1.2.dist-info/METADATA
discordion-0.1.2.dist-info/WHEEL
discordion-0.1.2.dist-info/top_level.txt
discordion-0.1.2.dist-info/RECORD
