Metadata-Version: 2.1
Name: discordion
Version: 0.1.2
Summary: A Discord bot powered by GPT for various tasks.
Home-page: https://github.com/odder/discordion
Author: Odder
Author-email: oscarrothandersen@gmail.com
License: UNKNOWN
Keywords: discord bot GPT
Platform: UNKNOWN
Classifier: Intended Audience :: Developers
Classifier: Programming Language :: Python :: 3.12
Classifier: Programming Language :: Python :: 3.11
Classifier: Programming Language :: Python :: 3.10
Classifier: Programming Language :: Python :: 3.9
Requires-Dist: discord.py
Requires-Dist: sqlitedict
Requires-Dist: openai
